MANIFEST.in
setup.py
idcard/__init__.py
idcard/areas.json
idcard.egg-info/PKG-INFO
idcard.egg-info/SOURCES.txt
idcard.egg-info/dependency_links.txt
idcard.egg-info/not-zip-safe
idcard.egg-info/top_level.txt