Metadata-Version: 1.0
Name: idcard
Version: 0.1
Summary: get information from id card number
Home-page: http://github.com/exherb/idcard
Author: Michael Herb
Author-email: i@4leaf.me
License: LICENCE
Platform: UNKNOWN
